benchopt/__init__.py
benchopt/__main__.py
benchopt/base.py
benchopt/benchmark.py
benchopt/callback.py
benchopt/config.py
benchopt/runner.py
benchopt/stopping_criterion.py
benchopt/cli/__init__.py
benchopt/cli/completion.py
benchopt/cli/helpers.py
benchopt/cli/main.py
benchopt/cli/process_results.py
benchopt/cli/tests/completion_cases.py
benchopt/cli/tests/test_cli.py
benchopt/cli/tests/test_cmd_install.py
benchopt/cli/tests/test_cmd_test.py
benchopt/cli/tests/test_helpers.py
benchopt/datasets/__init__.py
benchopt/datasets/simulated.py
benchopt/datasets/tests/test_dataset_simulated.py
benchopt/helpers/__init__.py
benchopt/helpers/julia.py
benchopt/helpers/r_lang.py
benchopt/helpers/requires_gpu.py
benchopt/helpers/run_examples.py
benchopt/helpers/shell.py
benchopt/helpers/tests/test_example_run.py
benchopt/helpers/tests/test_language_helpers.py
benchopt/parallel_backends/__init__.py
benchopt/parallel_backends/dask_backend.py
benchopt/parallel_backends/slurm_executor.py
benchopt/parallel_backends/tests/test_parallel_backends.py
benchopt/parallel_backends/tests/test_slurm_executor.py
benchopt/plotting/__init__.py
benchopt/plotting/base.py
benchopt/plotting/default_plots.py
benchopt/plotting/generate_html.py
benchopt/plotting/generate_matplotlib.py
benchopt/plotting/helpers.py
benchopt/plotting/html/static/arrow_left.svg
benchopt/plotting/html/static/benchmark.js
benchopt/plotting/html/static/download.svg
benchopt/plotting/html/static/home.svg
benchopt/plotting/html/static/hover_index.css
benchopt/plotting/html/static/main.css
benchopt/plotting/html/static/result.js
benchopt/plotting/html/static/symbols.js
benchopt/plotting/html/static/utilities.css
benchopt/plotting/html/templates/benchmark.mako.html
benchopt/plotting/html/templates/index.mako.html
benchopt/plotting/html/templates/result.mako.html
benchopt/plotting/tests/test_custom_plot.py
benchopt/tests/__init__.py
benchopt/tests/fixtures.py
benchopt/tests/test_benchmark_features.py
benchopt-1.8.0.dist-info/licenses/LICENSE
benchopt-1.8.0.dist-info/METADATA
benchopt-1.8.0.dist-info/WHEEL
benchopt-1.8.0.dist-info/entry_points.txt
benchopt-1.8.0.dist-info/top_level.txt
benchopt-1.8.0.dist-info/RECORD
