Metadata-Version: 2.4
Name: benchopt
Version: 1.8.0
Summary: Benchmark toolkit for optimization
Maintainer-email: Thomas Moreau <thomas.moreau@inria.fr>
License-Expression: BSD-3-Clause
Project-URL: Documentation, https://benchopt.github.io/
Project-URL: Source, https://github.com/benchopt/benchopt
Project-URL: Tracker, https://github.com/benchopt/benchopt/issues
Classifier: Development Status :: 5 - Production/Stable
Classifier: Topic :: System :: Benchmark
Classifier: Topic :: Software Development :: Libraries
Classifier: Topic :: Scientific/Engineering :: Artificial Intelligence
Classifier: Operating System :: OS Independent
Classifier: Intended Audience :: Developers
Classifier: Intended Audience :: Science/Research
Classifier: Environment :: Console
Classifier: Programming Language :: Python :: 3.10
Classifier: Programming Language :: Python :: 3.11
Classifier: Programming Language :: Python :: 3.12
Classifier: Programming Language :: Python :: 3.13
Classifier: Programming Language :: R
Classifier: Programming Language :: Other
Requires-Python: >=3.9
License-File: LICENSE
Requires-Dist: pyyaml
Requires-Dist: click>=8.0
Requires-Dist: pygithub
Requires-Dist: psutil
Requires-Dist: line-profiler
Requires-Dist: joblib>=1.4
Requires-Dist: mako
Requires-Dist: pyarrow
Requires-Dist: matplotlib
Requires-Dist: plotly>=4.12
Requires-Dist: numpy
Requires-Dist: scipy
Requires-Dist: pandas
Provides-Extra: test
Requires-Dist: pytest; extra == "test"
Requires-Dist: pytest-cov; extra == "test"
Requires-Dist: pytest-timeout; extra == "test"
Requires-Dist: coverage; extra == "test"
Provides-Extra: doc
Requires-Dist: numpydoc; extra == "doc"
Requires-Dist: sphinx; extra == "doc"
Requires-Dist: sphinx-book-theme; extra == "doc"
Requires-Dist: sphinx-design; extra == "doc"
Requires-Dist: sphinx-click; extra == "doc"
Requires-Dist: sphinx_gallery; extra == "doc"
Requires-Dist: sphinx-prompt; extra == "doc"
Requires-Dist: sphinx-copybutton; extra == "doc"
Requires-Dist: pillow; extra == "doc"
Requires-Dist: scikit-learn; extra == "doc"
Requires-Dist: rich; extra == "doc"
Provides-Extra: submitit
Requires-Dist: submitit; extra == "submitit"
Requires-Dist: rich; extra == "submitit"
Provides-Extra: dask
Requires-Dist: coiled; extra == "dask"
Requires-Dist: distributed; extra == "dask"
Requires-Dist: dask_jobqueue; extra == "dask"
Dynamic: license-file
